{
  "appPageId" : "92f3824a-4c4a-462f-b1dd-367efc2be930",
  "componentName" : "siteforce:sldsTwoCol84Layout",
  "dataProviders" : [ ],
  "id" : "0c2daee3-59b1-411e-a451-a37d8a30dc15",
  "label" : "Question Detail",
  "regions" : [ {
    "components" : [ {
      "componentAttributes" : {
        "bannerText" : "",
        "bannerTextWithKnowledge" : "Explore other <a href=\"javascript:void(0)\" class=\"headlineArticles\">articles</a> and <a href=\"javascript:void(0)\" class=\"headlineDiscussions\">discussions</a> on this topic.",
        "bannerTextWithoutKnowledge" : "Explore other <a href=\"javascript:void(0)\" class=\"headlineDiscussions\">discussions</a> on this topic.",
        "pageType" : "discussion",
        "showSubTopics" : true,
        "title" : "Welcome!",
        "uniqueNameOrId" : "{!recordId}"
      },
      "componentName" : "forceCommunity:headline",
      "id" : "b003ad26-67ca-44e0-bcde-7d260edda22e",
      "renderPriority" : "NEUTRAL",
      "renditionMap" : { },
      "type" : "component"
    } ],
    "id" : "fca5e81e-76cc-4bd2-84da-2ee562604fbe",
    "regionName" : "header",
    "type" : "region"
  }, {
    "components" : [ {
      "componentAttributes" : {
        "id" : "{!feedItemId}"
      },
      "componentName" : "forceCommunity:feedItemDetail",
      "id" : "0ebd2499-8fdc-4efc-84ba-727b6eebb009",
      "renderPriority" : "NEUTRAL",
      "renditionMap" : { },
      "type" : "component"
    } ],
    "id" : "e9711360-3474-4025-81cd-ea6d07ce80f6",
    "regionName" : "content",
    "type" : "region"
  }, {
    "components" : [ {
      "componentAttributes" : {
        "numberOfItems" : 5,
        "showViewCounts" : true,
        "title" : "Related Questions"
      },
      "componentName" : "selfService:similarQuestions",
      "id" : "b7ed00cd-96bf-4773-8ed5-1cfd47f1bfd6",
      "renderPriority" : "NEUTRAL",
      "renditionMap" : { },
      "type" : "component"
    }, {
      "componentAttributes" : {
        "channel" : "DefaultChannel",
        "title" : ""
      },
      "componentName" : "forceCommunity:recommendations",
      "id" : "aba94b09-69b8-4d56-8cdc-11c13715a31f",
      "renderPriority" : "NEUTRAL",
      "renditionMap" : { },
      "type" : "component"
    } ],
    "id" : "07f525c0-5bfc-4cb5-8a37-73558a2d70de",
    "regionName" : "sidebar",
    "type" : "region"
  }, {
    "components" : [ {
      "componentAttributes" : {
        "askCommunityLabel" : "Ask a Question",
        "buttonBgColor" : "",
        "buttonBgHoverColor" : "",
        "buttonBorderColor" : "",
        "buttonRadius" : 0,
        "buttonTextColor" : "",
        "buttonTextHoverColor" : "",
        "buttonTwoBgColor" : "",
        "buttonTwoBgHoverColor" : "",
        "buttonTwoBorderColor" : "",
        "buttonTwoRadius" : 0,
        "buttonTwoTextColor" : "",
        "buttonTwoTextHoverColor" : "",
        "confirmationMessage" : "Got it!",
        "contactSupportLabel" : "Contact Support",
        "followUpPromptLabel" : "Can we close your question?",
        "headerLabel" : "Don't see what you're looking for?",
        "isAskFollowPromptEnabled" : true,
        "isIncludeArticlesEnabled" : false,
        "isIncludeDiscussionsEnabled" : true,
        "isInitialSatisfactionPromptEnabled" : true,
        "isPublisherDeflectionEnabled" : true,
        "maxSuggestions" : 5,
        "satisfactionPromptLabel" : "Did we help to answer your question?",
        "showDetails" : false,
        "showTopics" : true
      },
      "componentName" : "siteforce:napiliFooter",
      "id" : "05104c92-b2eb-434e-b449-bf6bcccde5db",
      "renderPriority" : "NEUTRAL",
      "renditionMap" : { },
      "type" : "component"
    } ],
    "id" : "57e6f414-864e-4830-b2c4-03814a4b6171",
    "regionName" : "footer",
    "type" : "region"
  }, {
    "components" : [ {
      "componentAttributes" : {
        "customHeadTags" : "",
        "description" : "",
        "title" : "{!Record.Title}"
      },
      "componentName" : "forceCommunity:seoAssistant",
      "id" : "06212a23-f9f9-4f5f-bdfd-648c54d5032d",
      "renditionMap" : { },
      "type" : "component"
    } ],
    "id" : "826e2d94-2270-4688-a5c1-63b74b8b59b4",
    "regionName" : "sfdcHiddenRegion",
    "type" : "region"
  } ],
  "themeLayoutType" : "Inner",
  "type" : "view",
  "viewType" : "feeditem"
}